marieSimulator/Marie.py
marieSimulator/MarieGUI.py
marieSimulator/MarieReader.py
marieSimulator/__init__.py
marieSimulator-1.1.8.dist-info/LICENSE
marieSimulator-1.1.8.dist-info/METADATA
marieSimulator-1.1.8.dist-info/WHEEL
marieSimulator-1.1.8.dist-info/top_level.txt
marieSimulator-1.1.8.dist-info/RECORD
