Metadata-Version: 2.1
Name: marieSimulator
Version: 1.1.8
Summary: A Python Package to simulate a MARIE architecture on any computer
Home-page: https://github.com/dehadeaaryan/MarieSimulator
Author: Aaryan Dehade
Author-email: dehadeaaryan@gmail.com
Project-URL: Bug Tracker, https://github.com/dehadeaaryan/MarieSimulator/issues
Classifier: Programming Language :: Python :: 3
Classifier: License :: OSI Approved :: MIT License
Classifier: Operating System :: OS Independent
Requires-Python: >=3.6
License-File: LICENSE
